linkml_term_validator/__init__.py
linkml_term_validator/_version.py
linkml_term_validator/cli.py
linkml_term_validator/models.py
linkml_term_validator/validator.py
linkml_term_validator/validator_legacy.py
linkml_term_validator/plugins/__init__.py
linkml_term_validator/plugins/base.py
linkml_term_validator/plugins/binding_plugin.py
linkml_term_validator/plugins/dynamic_enum_plugin.py
linkml_term_validator/plugins/permissible_value_plugin.py
linkml_term_validator-0.2.1.dist-info/METADATA
linkml_term_validator-0.2.1.dist-info/WHEEL
linkml_term_validator-0.2.1.dist-info/entry_points.txt
linkml_term_validator-0.2.1.dist-info/licenses/LICENSE
linkml_term_validator-0.2.1.dist-info/RECORD
