Metadata-Version: 2.4
Name: linkml_term_validator
Version: 0.2.1
Summary: Validating external terms
Author-email: My Name <cjmungall@lbl.gov>
License-Expression: Apache-2.0
License-File: LICENSE
Requires-Python: <4.0,>=3.10
Requires-Dist: linkml-runtime>=1.9.4
Requires-Dist: linkml>=1.9.3
Requires-Dist: oaklib>=0.6.23
Requires-Dist: pydantic>=2.0.0
Requires-Dist: ruamel-yaml>=0.18.15
Requires-Dist: typer>=0.9.0
